phoenix_ai_memory/__init__.py
phoenix_ai_memory/memory/__init__.py
phoenix_ai_memory/memory/adapters/__init__.py
phoenix_ai_memory/memory/adapters/in_memory_store.py
phoenix_ai_memory/memory/adapters/langmem_store.py
phoenix_ai_memory/memory/adapters/mem0_store.py
phoenix_ai_memory/memory/adapters/zep_store.py
phoenix_ai_memory/memory/core.py
phoenix_ai_memory/memory/manager.py
phoenix_ai_memory/memory/policies/__init__.py
phoenix_ai_memory/memory/policies/basic.py
phoenix_ai_memory-0.2.9.dist-info/LICENSE
phoenix_ai_memory-0.2.9.dist-info/METADATA
phoenix_ai_memory-0.2.9.dist-info/WHEEL
phoenix_ai_memory-0.2.9.dist-info/entry_points.txt
phoenix_ai_memory-0.2.9.dist-info/RECORD
