Metadata-Version: 2.3
Name: phoenix-ai-memory
Version: 0.2.9
Summary: Pluggable memory layer for Agentic AI frameworks
License: Apache-2.0
Author: Singtel AI CoE
Author-email: ai.coe@singtel.com
Requires-Python: >=3.11,<3.13
Classifier: License :: OSI Approved :: Apache Software License
Classifier: Programming Language :: Python :: 3
Classifier: Programming Language :: Python :: 3.11
Classifier: Programming Language :: Python :: 3.12
Provides-Extra: all
Provides-Extra: langmem
Requires-Dist: langmem (>=0.0,<0.1) ; extra == "langmem" or extra == "all"
